statespace/__init__.py
statespace/base.py
statespace/decorators.py
statespace/models.py
statespace/reporting/__init__.py
statespace/reporting/accessors.py
statespace/reporting/base.py
statespace/reporting/models.py
statespace/reporting/templates.py
statespace/tools.py
python_statespace-0.1.0.dist-info/LICENSE
python_statespace-0.1.0.dist-info/METADATA
python_statespace-0.1.0.dist-info/WHEEL
python_statespace-0.1.0.dist-info/RECORD
