Metadata-Version: 2.1
Name: python-statespace
Version: 0.1.0
Summary: Enhance your portfolio construction process using advanced Optuna fine-tuning techniques.
Home-page: https://github.com/ActurialCapital/statespace
License: BSD 3-Clause License
Author: ActurialCapital
Requires-Python: >=3.11,<4.0
Classifier: License :: Other/Proprietary License
Classifier: Programming Language :: Python :: 3
Classifier: Programming Language :: Python :: 3.11
Classifier: Programming Language :: Python :: 3.12
Requires-Dist: numpy (>=1.26.4,<2.0.0)
Requires-Dist: optuna (>=3.6.1,<4.0.0)
Requires-Dist: pandas (>=2.2.2,<3.0.0)
Requires-Dist: plotly (>=5.22.0,<6.0.0)
Project-URL: Repository, https://github.com/ActurialCapital/statespace
